xj_short_message/__init__.py
xj_short_message/apps.py
xj_short_message/common.py
xj_short_message/models.py
xj_short_message/urls.py
xj_short_message/apis/__init__.py
xj_short_message/apis/send_short_message.py
xj_short_message/services/__init__.py
xj_short_message/services/send_short_message_service.py
xj_short_message/utils/__init__.py
xj_short_message/utils/common.py
xj_short_message/utils/custom_response.py
xj_short_message/utils/j_config.py
xj_short_message/utils/j_dict.py
xj_short_message/utils/model_handle.py
xj_short_message/utils/utils.py
xj_short_message-1.0.2.dist-info/METADATA
xj_short_message-1.0.2.dist-info/WHEEL
xj_short_message-1.0.2.dist-info/top_level.txt
xj_short_message-1.0.2.dist-info/RECORD
