Metadata-Version: 2.1
Name: xj-short-message
Version: 1.0.2
Summary: 短信模块
Home-page: UNKNOWN
License: apache 3.0
Platform: UNKNOWN
Requires-Dist: aliyun-python-sdk-core
